{"title": "藝術／美術收藏｜質感擺飾｜生活家居｜誠品線上", "author": null, "hostname": "eslite.com", "date": null, "fingerprint": "1ab661bf6012c96", "id": null, "license": null, "comments": "", "raw_text": "朱銘美術館太極造型一卡通  朱銘美術館太極造型一卡通，，Juming Museum  Iwasaki Chihiro Air Vase/ 100th Anniversary/ C  Iwasaki Chihiro Air Vase/ 100th Anniversary/ C，，いわさきちひろ/ Iwasaki Chihiro  Iwasaki Chihiro Air Vase/ 100th Anniversary/ B  Iwasaki Chihiro Air Vase/ 100th Anniversary/ B，，いわさきちひろ/ Iwasaki Chihiro  Iwasaki Chihiro Air Vase/ 100th Anniversary/ A  Iwasaki Chihiro Air Vase/ 100th Anniversary/ A，，いわさきちひろ/ Iwasaki Chihiro  galison Andy Warhol Brillo Wooden Blocks  galison Andy Warhol Brillo Wooden Blocks，，galison", "text": "朱銘美術館太極造型一卡通\n朱銘美術館太極造型一卡通，，Juming Museum\nIwasaki Chihiro Air Vase/ 100th Anniversary/ C\nIwasaki Chihiro Air Vase/ 100th Anniversary/ C，，いわさきちひろ/ Iwasaki Chihiro\nIwasaki Chihiro Air Vase/ 100th Anniversary/ B\nIwasaki Chihiro Air Vase/ 100th Anniversary/ B，，いわさきちひろ/ Iwasaki Chihiro\nIwasaki Chihiro Air Vase/ 100th Anniversary/ A\nIwasaki Chihiro Air Vase/ 100th Anniversary/ A，，いわさきちひろ/ Iwasaki Chihiro\ngalison Andy Warhol Brillo Wooden Blocks\ngalison Andy Warhol Brillo Wooden Blocks，，galison", "language": null, "image": "https://www.eslite.com/eslite-og-logo.png", "pagetype": "Article", "source": "https://www.eslite.com/category/3/6683", "source-hostname": "藝術／美術收藏｜質感擺飾｜生活家居｜誠品線上", "excerpt": "藝術／美術收藏類-提供各種藝術／美術收藏新品及優惠商品。誠品以「人文、藝術、創意、生活」為核心價值，由推廣閱讀出發，並透過線上網路，傳遞博雅的溫度，打造全新的文化場域。", "categories": "", "tags": ""}