{"title": "SSD固態硬碟｜儲存設備｜3C家電｜誠品線上", "author": null, "hostname": "eslite.com", "date": "2023-07-06", "fingerprint": "2288b27221fd95a4", "id": null, "license": null, "comments": "", "raw_text": "ADATA威剛 LEGEND 850 1TB SSD固態硬碟 (ALEG-850-1TCS)贈散熱片  ADATA威剛 LEGEND 850 1TB SSD固態硬碟 (ALEG-850-1TCS)贈散熱片，，  ASUS華碩 TUF GAMING AS1000 1TB外接式SSD(ESD-T1B10)  ASUS華碩 TUF GAMING AS1000 1TB外接式SSD(ESD-T1B10)，，  Apacer宇瞻 AS2280P4 1TB M.2 PCIe Gen3x4 固態硬碟  Apacer宇瞻 AS2280P4 1TB M.2 PCIe Gen3x4 固態硬碟，，  WD 威騰 黑標 SN770 500G M.2 PCI-E SSD固態硬碟(WDS500G3X0E)  WD 威騰 黑標 SN770 500G M.2 PCI-E SSD固態硬碟(WDS500G3X0E)，，威騰  WD 威騰 黑標 SN770 1TB M.2 PCI-E SSD固態硬碟(WDS100T3X0E)  WD 威騰 黑標 SN770 1TB M.2 PCI-E SSD固態硬碟(WDS100T3X0E)，，威騰  ADATA 威剛 LEGEND 710 512G M.2 PCIe SSD固態硬碟  ADATA 威剛 LEGEND 710 512G M.2 PCIe SSD固態硬碟，，ADATA 威剛  ADATA 威剛 LEGEND 710 512G M.2 PCIe SSD固態硬碟  ADATA 威剛 LEGEND 710 512G M.2 PCIe SSD固態硬碟，，ADATA 威剛  Intel 670P系列 512GB M.2 PCIe/SSD固態硬碟  Intel 670P系列 512GB M.2 PCIe/SSD固態硬碟，，Intel  金士頓Kingston NV1 1TB NVMe PCIe SSD 固態硬碟  金士頓Kingston NV1 1TB NVMe PCIe SSD 固態硬碟，，金士頓  美光 250G MX500 SA3 TLC/5Y2.5吋 SATAIII SSD固態硬碟  美光 250G MX500 SA3 TLC/5Y2.5吋 SATAIII SSD固態硬碟，，美光  美光 500G P5 PLUS M.2 PCIE SSD 固態硬碟  美光 500G P5 PLUS M.2 PCIE SSD 固態硬碟，，美光  三星Samsung 980 PRO PCle 4.0 NVMe M.2 固態硬碟 500G  三星Samsung 980 PRO PCle 4.0 NVMe M.2 固態硬碟 500G，，三星  三星Samsung 980 PRO PCle 4.0 NVMe M.2 固態硬碟 1TB  三星Samsung 980 PRO PCle 4.0 NVMe M.2 固態硬碟 1TB，，三星  WD SN570 1TB M.2 PCI-E TLC/5Y(藍) 固態硬碟  WD SN570 1TB M.2 PCI-E TLC/5Y(藍) 固態硬碟，，WD  WD SN570 500G M.2 PCI-E TLC/5Y(藍) 固態硬碟  WD SN570 500G M.2 PCI-E TLC/5Y(藍) 固態硬碟，，WD  ADATA威剛 XPG SX8200Pro 512G M.2 2280 PCIe SSD固態硬碟  ADATA威剛 XPG SX8200Pro 512G M.2 2280 PCIe SSD固態硬碟，，威剛  ADATA威剛 XPG SX8200Pro 256G M.2 2280 PCIe SSD固態硬碟  ADATA威剛 XPG SX8200Pro 256G M.2 2280 PCIe SSD固態硬碟，，威剛  ADATA威剛 XPG SX8200Pro 1TB M.2 2280 PCIe SSD固態硬碟  ADATA威剛 XPG SX8200Pro 1TB M.2 2280 PCIe SSD固態硬碟，，威剛  【普雷伊】【PS5周邊】WD 黑標 SN850 1TB 固態硬碟 (含散熱片) M.2 2280 PCIe SSD  【普雷伊】【PS5周邊】WD 黑標 SN850 1TB 固態硬碟 (含散熱片) M.2 2280 PCIe SSD，，WD/ PlayStation", "text": "ADATA威剛 LEGEND 850 1TB SSD固態硬碟 (ALEG-850-1TCS)贈散熱片\nADATA威剛 LEGEND 850 1TB SSD固態硬碟 (ALEG-850-1TCS)贈散熱片，，\nASUS華碩 TUF GAMING AS1000 1TB外接式SSD(ESD-T1B10)\nASUS華碩 TUF GAMING AS1000 1TB外接式SSD(ESD-T1B10)，，\nApacer宇瞻 AS2280P4 1TB M.2 PCIe Gen3x4 固態硬碟\nApacer宇瞻 AS2280P4 1TB M.2 PCIe Gen3x4 固態硬碟，，\nWD 威騰 黑標 SN770 500G M.2 PCI-E SSD固態硬碟(WDS500G3X0E)\nWD 威騰 黑標 SN770 500G M.2 PCI-E SSD固態硬碟(WDS500G3X0E)，，威騰\nWD 威騰 黑標 SN770 1TB M.2 PCI-E SSD固態硬碟(WDS100T3X0E)\nWD 威騰 黑標 SN770 1TB M.2 PCI-E SSD固態硬碟(WDS100T3X0E)，，威騰\nADATA 威剛 LEGEND 710 512G M.2 PCIe SSD固態硬碟\nADATA 威剛 LEGEND 710 512G M.2 PCIe SSD固態硬碟，，ADATA 威剛\nADATA 威剛 LEGEND 710 512G M.2 PCIe SSD固態硬碟\nADATA 威剛 LEGEND 710 512G M.2 PCIe SSD固態硬碟，，ADATA 威剛\nIntel 670P系列 512GB M.2 PCIe/SSD固態硬碟\nIntel 670P系列 512GB M.2 PCIe/SSD固態硬碟，，Intel\n金士頓Kingston NV1 1TB NVMe PCIe SSD 固態硬碟\n金士頓Kingston NV1 1TB NVMe PCIe SSD 固態硬碟，，金士頓\n美光 250G MX500 SA3 TLC/5Y2.5吋 SATAIII SSD固態硬碟\n美光 250G MX500 SA3 TLC/5Y2.5吋 SATAIII SSD固態硬碟，，美光\n美光 500G P5 PLUS M.2 PCIE SSD 固態硬碟\n美光 500G P5 PLUS M.2 PCIE SSD 固態硬碟，，美光\n三星Samsung 980 PRO PCle 4.0 NVMe M.2 固態硬碟 500G\n三星Samsung 980 PRO PCle 4.0 NVMe M.2 固態硬碟 500G，，三星\n三星Samsung 980 PRO PCle 4.0 NVMe M.2 固態硬碟 1TB\n三星Samsung 980 PRO PCle 4.0 NVMe M.2 固態硬碟 1TB，，三星\nWD SN570 1TB M.2 PCI-E TLC/5Y(藍) 固態硬碟\nWD SN570 1TB M.2 PCI-E TLC/5Y(藍) 固態硬碟，，WD\nWD SN570 500G M.2 PCI-E TLC/5Y(藍) 固態硬碟\nWD SN570 500G M.2 PCI-E TLC/5Y(藍) 固態硬碟，，WD\nADATA威剛 XPG SX8200Pro 512G M.2 2280 PCIe SSD固態硬碟\nADATA威剛 XPG SX8200Pro 512G M.2 2280 PCIe SSD固態硬碟，，威剛\nADATA威剛 XPG SX8200Pro 256G M.2 2280 PCIe SSD固態硬碟\nADATA威剛 XPG SX8200Pro 256G M.2 2280 PCIe SSD固態硬碟，，威剛\nADATA威剛 XPG SX8200Pro 1TB M.2 2280 PCIe SSD固態硬碟\nADATA威剛 XPG SX8200Pro 1TB M.2 2280 PCIe SSD固態硬碟，，威剛\n【普雷伊】【PS5周邊】WD 黑標 SN850 1TB 固態硬碟 (含散熱片) M.2 2280 PCIe SSD\n【普雷伊】【PS5周邊】WD 黑標 SN850 1TB 固態硬碟 (含散熱片) M.2 2280 PCIe SSD，，WD/ PlayStation", "language": null, "image": "https://www.eslite.com/eslite-og-logo.png", "pagetype": "Article", "source": "https://www.eslite.com/category/3/6450", "source-hostname": "SSD固態硬碟｜儲存設備｜3C家電｜誠品線上", "excerpt": "SSD固態硬碟類-提供各種SSD固態硬碟新品及優惠商品。誠品以「人文、藝術、創意、生活」為核心價值，由推廣閱讀出發，並透過線上網路，傳遞博雅的溫度，打造全新的文化場域。", "categories": "", "tags": ""}