{"title": "造型髮品｜髮妝造型｜美妝保養｜誠品線上", "author": null, "hostname": "eslite.com", "date": "2023-07-20", "fingerprint": "ebcdbebb4f7837be", "id": null, "license": null, "comments": "", "raw_text": "Conalife 潮流抓夾40CM馬尾波浪髮夾(淺棕色)  Conalife 潮流抓夾40CM馬尾波浪髮夾(淺棕色)，，Conalife  Conalife 潮流抓夾40CM馬尾波浪髮夾(深棕色)  Conalife 潮流抓夾40CM馬尾波浪髮夾(深棕色)，，Conalife  Conalife 潮流抓夾40CM馬尾波浪髮夾(棕黑色)  Conalife 潮流抓夾40CM馬尾波浪髮夾(棕黑色)，，Conalife  ghd聚熱圓梳＃4 55mm  ghd聚熱圓梳＃4 55mm，，ghd  ghd聚熱圓梳＃3 45mm  ghd聚熱圓梳＃3 45mm，，ghd  ghd聚熱圓梳＃2 35mm  ghd聚熱圓梳＃2 35mm，，ghd  ghd聚熱圓梳＃1 25mm  ghd聚熱圓梳＃1 25mm，，ghd  ghd尖尾梳  ghd尖尾梳，，ghd  ghd專業寬齒梳  ghd專業寬齒梳，，ghd  ghd全方位造型圓梳＃4 55mm  ghd全方位造型圓梳＃4 55mm，，ghd  ghd全方位造型圓梳＃3 44mm  ghd全方位造型圓梳＃3 44mm，，ghd  ghd全方位造型圓梳＃2 35mm  ghd全方位造型圓梳＃2 35mm，，ghd  ghd全方位造型圓梳＃1 28mm  ghd全方位造型圓梳＃1 28mm，，ghd  ghd包頭梳  ghd包頭梳，，ghd  ghd方形板梳  ghd方形板梳，，ghd  MOROCCANOIL優油高效保濕精華300ML  MOROCCANOIL優油高效保濕精華300ML，，MOROCCANOIL  MOROCCANOIL優油閃亮噴霧100ML  MOROCCANOIL優油閃亮噴霧100ML，，MOROCCANOIL  MOROCCANOIL優油輕盈豐量造型乳100ML  MOROCCANOIL優油輕盈豐量造型乳100ML，，MOROCCANOIL  MOROCCANOIL優油輕盈豐量慕思250ML  MOROCCANOIL優油輕盈豐量慕思250ML，，MOROCCANOIL  MOROCCANOIL優油質地改變塑型土75ML  MOROCCANOIL優油質地改變塑型土75ML，，MOROCCANOIL  MOROCCANOIL優油輕盈豐量噴霧160ML  MOROCCANOIL優油輕盈豐量噴霧160ML，，MOROCCANOIL  MOROCCANOIL優油質地改變噴霧205ML  MOROCCANOIL優油質地改變噴霧205ML，，MOROCCANOIL  MOROCCANOIL優油熱防護噴霧225ML  MOROCCANOIL優油熱防護噴霧225ML，，MOROCCANOIL  MOROCCANOIL優油捲度記憶塑型乳250ML  MOROCCANOIL優油捲度記憶塑型乳250ML，，MOROCCANOIL  MOROCCANOIL優油打光超強定型霧330ML  MOROCCANOIL優油打光超強定型霧330ML，，MOROCCANOIL  MOROCCANOIL優油打光強力定型霧330ML  MOROCCANOIL優油打光強力定型霧330ML，，MOROCCANOIL  MOROCCANOIL優油打光定型霧330ML  MOROCCANOIL優油打光定型霧330ML，，MOROCCANOIL  MOROCCANOIL優油彈力塑捲噴霧160ML  MOROCCANOIL優油彈力塑捲噴霧160ML，，MOROCCANOIL  MOROCCANOIL優油強力控捲慕思150ML  MOROCCANOIL優油強力控捲慕思150ML，，MOROCCANOIL  MOROCCANOIL優油塑型乳100ML  MOROCCANOIL優油塑型乳100ML，，MOROCCANOIL  ECRU鬆感質地噴霧225ML  ECRU鬆感質地噴霧225ML，，ECRU  ECRU輕感順髮霜50ML  ECRU輕感順髮霜50ML，，ECRU  ECRU質地造型土50ML  ECRU質地造型土50ML，，ECRU  ECRU海洋豐盈水凝膠148ML  ECRU海洋豐盈水凝膠148ML，，ECRU  ECRU晶瑩蓬鬆噴霧148ML  ECRU晶瑩蓬鬆噴霧148ML，，ECRU  ECRU強塑乾髮蠟50ML  ECRU強塑乾髮蠟50ML，，ECRU  ECRU多功能塑型髮膠148ML  ECRU多功能塑型髮膠148ML，，ECRU  ECRU光感強力乾髮膠200ML  ECRU光感強力乾髮膠200ML，，ECRU  ECRU光感造型乾髮膠200ML  ECRU光感造型乾髮膠200ML，，ECRU  Conalife 全真髮一片式隱形15CM增厚墊髮片 (淺棕色)  Conalife 全真髮一片式隱形15CM增厚墊髮片 (淺棕色)，，Conalife", "text": "Conalife 潮流抓夾40CM馬尾波浪髮夾(淺棕色)\nConalife 潮流抓夾40CM馬尾波浪髮夾(淺棕色)，，Conalife\nConalife 潮流抓夾40CM馬尾波浪髮夾(深棕色)\nConalife 潮流抓夾40CM馬尾波浪髮夾(深棕色)，，Conalife\nConalife 潮流抓夾40CM馬尾波浪髮夾(棕黑色)\nConalife 潮流抓夾40CM馬尾波浪髮夾(棕黑色)，，Conalife\nghd聚熱圓梳＃4 55mm\nghd聚熱圓梳＃4 55mm，，ghd\nghd聚熱圓梳＃3 45mm\nghd聚熱圓梳＃3 45mm，，ghd\nghd聚熱圓梳＃2 35mm\nghd聚熱圓梳＃2 35mm，，ghd\nghd聚熱圓梳＃1 25mm\nghd聚熱圓梳＃1 25mm，，ghd\nghd尖尾梳\nghd尖尾梳，，ghd\nghd專業寬齒梳\nghd專業寬齒梳，，ghd\nghd全方位造型圓梳＃4 55mm\nghd全方位造型圓梳＃4 55mm，，ghd\nghd全方位造型圓梳＃3 44mm\nghd全方位造型圓梳＃3 44mm，，ghd\nghd全方位造型圓梳＃2 35mm\nghd全方位造型圓梳＃2 35mm，，ghd\nghd全方位造型圓梳＃1 28mm\nghd全方位造型圓梳＃1 28mm，，ghd\nghd包頭梳\nghd包頭梳，，ghd\nghd方形板梳\nghd方形板梳，，ghd\nMOROCCANOIL優油高效保濕精華300ML\nMOROCCANOIL優油高效保濕精華300ML，，MOROCCANOIL\nMOROCCANOIL優油閃亮噴霧100ML\nMOROCCANOIL優油閃亮噴霧100ML，，MOROCCANOIL\nMOROCCANOIL優油輕盈豐量造型乳100ML\nMOROCCANOIL優油輕盈豐量造型乳100ML，，MOROCCANOIL\nMOROCCANOIL優油輕盈豐量慕思250ML\nMOROCCANOIL優油輕盈豐量慕思250ML，，MOROCCANOIL\nMOROCCANOIL優油質地改變塑型土75ML\nMOROCCANOIL優油質地改變塑型土75ML，，MOROCCANOIL\nMOROCCANOIL優油輕盈豐量噴霧160ML\nMOROCCANOIL優油輕盈豐量噴霧160ML，，MOROCCANOIL\nMOROCCANOIL優油質地改變噴霧205ML\nMOROCCANOIL優油質地改變噴霧205ML，，MOROCCANOIL\nMOROCCANOIL優油熱防護噴霧225ML\nMOROCCANOIL優油熱防護噴霧225ML，，MOROCCANOIL\nMOROCCANOIL優油捲度記憶塑型乳250ML\nMOROCCANOIL優油捲度記憶塑型乳250ML，，MOROCCANOIL\nMOROCCANOIL優油打光超強定型霧330ML\nMOROCCANOIL優油打光超強定型霧330ML，，MOROCCANOIL\nMOROCCANOIL優油打光強力定型霧330ML\nMOROCCANOIL優油打光強力定型霧330ML，，MOROCCANOIL\nMOROCCANOIL優油打光定型霧330ML\nMOROCCANOIL優油打光定型霧330ML，，MOROCCANOIL\nMOROCCANOIL優油彈力塑捲噴霧160ML\nMOROCCANOIL優油彈力塑捲噴霧160ML，，MOROCCANOIL\nMOROCCANOIL優油強力控捲慕思150ML\nMOROCCANOIL優油強力控捲慕思150ML，，MOROCCANOIL\nMOROCCANOIL優油塑型乳100ML\nMOROCCANOIL優油塑型乳100ML，，MOROCCANOIL\nECRU鬆感質地噴霧225ML\nECRU鬆感質地噴霧225ML，，ECRU\nECRU輕感順髮霜50ML\nECRU輕感順髮霜50ML，，ECRU\nECRU質地造型土50ML\nECRU質地造型土50ML，，ECRU\nECRU海洋豐盈水凝膠148ML\nECRU海洋豐盈水凝膠148ML，，ECRU\nECRU晶瑩蓬鬆噴霧148ML\nECRU晶瑩蓬鬆噴霧148ML，，ECRU\nECRU強塑乾髮蠟50ML\nECRU強塑乾髮蠟50ML，，ECRU\nECRU多功能塑型髮膠148ML\nECRU多功能塑型髮膠148ML，，ECRU\nECRU光感強力乾髮膠200ML\nECRU光感強力乾髮膠200ML，，ECRU\nECRU光感造型乾髮膠200ML\nECRU光感造型乾髮膠200ML，，ECRU\nConalife 全真髮一片式隱形15CM增厚墊髮片 (淺棕色)\nConalife 全真髮一片式隱形15CM增厚墊髮片 (淺棕色)，，Conalife", "language": null, "image": "https://www.eslite.com/eslite-og-logo.png", "pagetype": "Article", "source": "https://www.eslite.com/category/3/3391", "source-hostname": "造型髮品｜髮妝造型｜美妝保養｜誠品線上", "excerpt": "造型髮品類-提供各種造型髮品新品及優惠商品。誠品以「人文、藝術、創意、生活」為核心價值，由推廣閱讀出發，並透過線上網路，傳遞博雅的溫度，打造全新的文化場域。", "categories": "", "tags": ""}