{"title": "短褲．長褲．牛仔褲｜法國小狐狸｜服飾鞋包｜誠品線上", "author": null, "hostname": "eslite.com", "date": "2023-07-07", "fingerprint": "7768209d0654b696", "id": null, "license": null, "comments": "", "raw_text": "MAISON KITSUNE 灰色變化狐狸頭LOGO束口褲/女裝/ XS  MAISON KITSUNE 灰色變化狐狸頭LOGO束口褲/女裝/ XS，，  MAISON KITSUNE 灰色變化狐狸頭LOGO束口褲/女裝/ S  MAISON KITSUNE 灰色變化狐狸頭LOGO束口褲/女裝/ S，，  MAISON KITSUNE 灰色變化狐狸頭LOGO束口褲/女裝/ M  MAISON KITSUNE 灰色變化狐狸頭LOGO束口褲/女裝/ M，，  MAISON KITSUNE 深綠色變化狐狸頭LOGO長褲/ XS  MAISON KITSUNE 深綠色變化狐狸頭LOGO長褲/ XS，，  MAISON KITSUNE 深綠色變化狐狸頭LOGO長褲/ S  MAISON KITSUNE 深綠色變化狐狸頭LOGO長褲/ S，，  MAISON KITSUNE 深綠色變化狐狸頭LOGO長褲/ M  MAISON KITSUNE 深綠色變化狐狸頭LOGO長褲/ M，，  MAISON KITSUNE 深綠色變化狐狸頭LOGO長褲/ L  MAISON KITSUNE 深綠色變化狐狸頭LOGO長褲/ L，，  MAISON KITSUNE 灰色狐狸頭LOGO長褲/ XS  MAISON KITSUNE 灰色狐狸頭LOGO長褲/ XS，，  MAISON KITSUNE 灰色狐狸頭LOGO長褲/ S  MAISON KITSUNE 灰色狐狸頭LOGO長褲/ S，，  MAISON KITSUNE 灰色狐狸頭LOGO長褲/ M  MAISON KITSUNE 灰色狐狸頭LOGO長褲/ M，，  MAISON KITSUNE 灰色狐狸頭LOGO長褲/ L  MAISON KITSUNE 灰色狐狸頭LOGO長褲/ L，，  MAISON KITSUNE 湖水綠狐狸頭LOGO長褲/ XS  MAISON KITSUNE 湖水綠狐狸頭LOGO長褲/ XS，，  MAISON KITSUNE 湖水綠狐狸頭LOGO長褲/ S  MAISON KITSUNE 湖水綠狐狸頭LOGO長褲/ S，，  MAISON KITSUNE 湖水綠狐狸頭LOGO長褲/ M  MAISON KITSUNE 湖水綠狐狸頭LOGO長褲/ M，，  MAISON KITSUNE 湖水綠狐狸頭LOGO長褲/ L  MAISON KITSUNE 湖水綠狐狸頭LOGO長褲/ L，，  MAISON KITSUNE 黑色悠閒狐狸LOGO長束口褲/中性 / M  MAISON KITSUNE 黑色悠閒狐狸LOGO長束口褲/中性 / M，，  MAISON KITSUNE 黑色悠閒狐狸LOGO長束口褲/中性 / XXS  MAISON KITSUNE 黑色悠閒狐狸LOGO長束口褲/中性 / XXS，，  MAISON KITSUNE 黑色悠閒狐狸LOGO長束口褲/中性 / XL  MAISON KITSUNE 黑色悠閒狐狸LOGO長束口褲/中性 / XL，，  MAISON KITSUNE 灰色悠閒狐狸LOGO長束口褲/中性 / XSS  MAISON KITSUNE 灰色悠閒狐狸LOGO長束口褲/中性 / XSS，，  MAISON KITSUNE 黑色悠閒狐狸LOGO長束口褲/中性 / S  MAISON KITSUNE 黑色悠閒狐狸LOGO長束口褲/中性 / S，，  MAISON KITSUNE 黑色悠閒狐狸LOGO長束口褲/中性 / L  MAISON KITSUNE 黑色悠閒狐狸LOGO長束口褲/中性 / L，，  MAISON KITSUNE 灰色悠閒狐狸LOGO長束口褲/中性 / M  MAISON KITSUNE 灰色悠閒狐狸LOGO長束口褲/中性 / M，，  MAISON KITSUNE 黑色悠閒狐狸LOGO長束口褲/中性 / XS  MAISON KITSUNE 黑色悠閒狐狸LOGO長束口褲/中性 / XS，，  MAISON KITSUNE 灰色悠閒狐狸LOGO長束口褲/中性 / S  MAISON KITSUNE 灰色悠閒狐狸LOGO長束口褲/中性 / S，，  MAISON KITSUNÉ 深藍色直筒長褲--40  MAISON KITSUNÉ 深藍色直筒長褲--40，，MAISON KITSUNÉ  MAISON KITSUNÉ 深藍色直筒長褲--42  MAISON KITSUNÉ 深藍色直筒長褲--42，，MAISON KITSUNÉ  MAISON KITSUNÉ 深藍色直筒長褲--38  MAISON KITSUNÉ 深藍色直筒長褲--38，，MAISON KITSUNÉ  MAISON KITSUNÉ 深藍色直筒長褲--36  MAISON KITSUNÉ 深藍色直筒長褲--36，，MAISON KITSUNÉ  MAISON KITSUNÉ 灰色ACTUA狐狸頭LOGO休閒短褲-XS  MAISON KITSUNÉ 灰色ACTUA狐狸頭LOGO休閒短褲-XS，，MAISON KITSUNÉ  MAISON KITSUNÉ 灰色ACTUA狐狸頭LOGO休閒短褲--M  MAISON KITSUNÉ 灰色ACTUA狐狸頭LOGO休閒短褲--M，，MAISON KITSUNÉ  MAISON KITSUNÉ 灰色ACTUA狐狸頭LOGO休閒短褲--S  MAISON KITSUNÉ 灰色ACTUA狐狸頭LOGO休閒短褲--S，，MAISON KITSUNÉ  MAISON KITSUNÉ 灰色ACTUA狐狸頭LOGO休閒短褲-XL  MAISON KITSUNÉ 灰色ACTUA狐狸頭LOGO休閒短褲-XL，，MAISON KITSUNÉ  MAISON KITSUNÉ 灰色ACTUA狐狸頭LOGO休閒短褲--L  MAISON KITSUNÉ 灰色ACTUA狐狸頭LOGO休閒短褲--L，，MAISON KITSUNÉ  MAISON KITSUNÉ 灰色ACTUA狐狸頭LOGO休閒五分褲-XS  MAISON KITSUNÉ 灰色ACTUA狐狸頭LOGO休閒五分褲-XS，，MAISON KITSUNÉ  MAISON KITSUNÉ 灰色ACTUA狐狸頭LOGO休閒五分褲-XL  MAISON KITSUNÉ 灰色ACTUA狐狸頭LOGO休閒五分褲-XL，，MAISON KITSUNÉ  MAISON KITSUNÉ 灰色ACTUA狐狸頭LOGO休閒五分褲--S  MAISON KITSUNÉ 灰色ACTUA狐狸頭LOGO休閒五分褲--S，，MAISON KITSUNÉ  MAISON KITSUNÉ 灰色ACTUA狐狸頭LOGO休閒五分褲--M  MAISON KITSUNÉ 灰色ACTUA狐狸頭LOGO休閒五分褲--M，，MAISON KITSUNÉ  MAISON KITSUNÉ 灰色ACTUA狐狸頭LOGO休閒五分褲--L  MAISON KITSUNÉ 灰色ACTUA狐狸頭LOGO休閒五分褲--L，，MAISON KITSUNÉ  MAISON KITSUNÉ 水藍ACTUA狐狸頭LOGO休閒短褲-XS  MAISON KITSUNÉ 水藍ACTUA狐狸頭LOGO休閒短褲-XS，，MAISON KITSUNÉ  MAISON KITSUNÉ 水藍ACTUA狐狸頭LOGO休閒短褲-XL  MAISON KITSUNÉ 水藍ACTUA狐狸頭LOGO休閒短褲-XL，，MAISON KITSUNÉ", "text": "MAISON KITSUNE 灰色變化狐狸頭LOGO束口褲/女裝/ XS\nMAISON KITSUNE 灰色變化狐狸頭LOGO束口褲/女裝/ XS，，\nMAISON KITSUNE 灰色變化狐狸頭LOGO束口褲/女裝/ S\nMAISON KITSUNE 灰色變化狐狸頭LOGO束口褲/女裝/ S，，\nMAISON KITSUNE 灰色變化狐狸頭LOGO束口褲/女裝/ M\nMAISON KITSUNE 灰色變化狐狸頭LOGO束口褲/女裝/ M，，\nMAISON KITSUNE 深綠色變化狐狸頭LOGO長褲/ XS\nMAISON KITSUNE 深綠色變化狐狸頭LOGO長褲/ XS，，\nMAISON KITSUNE 深綠色變化狐狸頭LOGO長褲/ S\nMAISON KITSUNE 深綠色變化狐狸頭LOGO長褲/ S，，\nMAISON KITSUNE 深綠色變化狐狸頭LOGO長褲/ M\nMAISON KITSUNE 深綠色變化狐狸頭LOGO長褲/ M，，\nMAISON KITSUNE 深綠色變化狐狸頭LOGO長褲/ L\nMAISON KITSUNE 深綠色變化狐狸頭LOGO長褲/ L，，\nMAISON KITSUNE 灰色狐狸頭LOGO長褲/ XS\nMAISON KITSUNE 灰色狐狸頭LOGO長褲/ XS，，\nMAISON KITSUNE 灰色狐狸頭LOGO長褲/ S\nMAISON KITSUNE 灰色狐狸頭LOGO長褲/ S，，\nMAISON KITSUNE 灰色狐狸頭LOGO長褲/ M\nMAISON KITSUNE 灰色狐狸頭LOGO長褲/ M，，\nMAISON KITSUNE 灰色狐狸頭LOGO長褲/ L\nMAISON KITSUNE 灰色狐狸頭LOGO長褲/ L，，\nMAISON KITSUNE 湖水綠狐狸頭LOGO長褲/ XS\nMAISON KITSUNE 湖水綠狐狸頭LOGO長褲/ XS，，\nMAISON KITSUNE 湖水綠狐狸頭LOGO長褲/ S\nMAISON KITSUNE 湖水綠狐狸頭LOGO長褲/ S，，\nMAISON KITSUNE 湖水綠狐狸頭LOGO長褲/ M\nMAISON KITSUNE 湖水綠狐狸頭LOGO長褲/ M，，\nMAISON KITSUNE 湖水綠狐狸頭LOGO長褲/ L\nMAISON KITSUNE 湖水綠狐狸頭LOGO長褲/ L，，\nMAISON KITSUNE 黑色悠閒狐狸LOGO長束口褲/中性 / M\nMAISON KITSUNE 黑色悠閒狐狸LOGO長束口褲/中性 / M，，\nMAISON KITSUNE 黑色悠閒狐狸LOGO長束口褲/中性 / XXS\nMAISON KITSUNE 黑色悠閒狐狸LOGO長束口褲/中性 / XXS，，\nMAISON KITSUNE 黑色悠閒狐狸LOGO長束口褲/中性 / XL\nMAISON KITSUNE 黑色悠閒狐狸LOGO長束口褲/中性 / XL，，\nMAISON KITSUNE 灰色悠閒狐狸LOGO長束口褲/中性 / XSS\nMAISON KITSUNE 灰色悠閒狐狸LOGO長束口褲/中性 / XSS，，\nMAISON KITSUNE 黑色悠閒狐狸LOGO長束口褲/中性 / S\nMAISON KITSUNE 黑色悠閒狐狸LOGO長束口褲/中性 / S，，\nMAISON KITSUNE 黑色悠閒狐狸LOGO長束口褲/中性 / L\nMAISON KITSUNE 黑色悠閒狐狸LOGO長束口褲/中性 / L，，\nMAISON KITSUNE 灰色悠閒狐狸LOGO長束口褲/中性 / M\nMAISON KITSUNE 灰色悠閒狐狸LOGO長束口褲/中性 / M，，\nMAISON KITSUNE 黑色悠閒狐狸LOGO長束口褲/中性 / XS\nMAISON KITSUNE 黑色悠閒狐狸LOGO長束口褲/中性 / XS，，\nMAISON KITSUNE 灰色悠閒狐狸LOGO長束口褲/中性 / S\nMAISON KITSUNE 灰色悠閒狐狸LOGO長束口褲/中性 / S，，\nMAISON KITSUNÉ 深藍色直筒長褲--40\nMAISON KITSUNÉ 深藍色直筒長褲--40，，MAISON KITSUNÉ\nMAISON KITSUNÉ 深藍色直筒長褲--42\nMAISON KITSUNÉ 深藍色直筒長褲--42，，MAISON KITSUNÉ\nMAISON KITSUNÉ 深藍色直筒長褲--38\nMAISON KITSUNÉ 深藍色直筒長褲--38，，MAISON KITSUNÉ\nMAISON KITSUNÉ 深藍色直筒長褲--36\nMAISON KITSUNÉ 深藍色直筒長褲--36，，MAISON KITSUNÉ\nMAISON KITSUNÉ 灰色ACTUA狐狸頭LOGO休閒短褲-XS\nMAISON KITSUNÉ 灰色ACTUA狐狸頭LOGO休閒短褲-XS，，MAISON KITSUNÉ\nMAISON KITSUNÉ 灰色ACTUA狐狸頭LOGO休閒短褲--M\nMAISON KITSUNÉ 灰色ACTUA狐狸頭LOGO休閒短褲--M，，MAISON KITSUNÉ\nMAISON KITSUNÉ 灰色ACTUA狐狸頭LOGO休閒短褲--S\nMAISON KITSUNÉ 灰色ACTUA狐狸頭LOGO休閒短褲--S，，MAISON KITSUNÉ\nMAISON KITSUNÉ 灰色ACTUA狐狸頭LOGO休閒短褲-XL\nMAISON KITSUNÉ 灰色ACTUA狐狸頭LOGO休閒短褲-XL，，MAISON KITSUNÉ\nMAISON KITSUNÉ 灰色ACTUA狐狸頭LOGO休閒短褲--L\nMAISON KITSUNÉ 灰色ACTUA狐狸頭LOGO休閒短褲--L，，MAISON KITSUNÉ\nMAISON KITSUNÉ 灰色ACTUA狐狸頭LOGO休閒五分褲-XS\nMAISON KITSUNÉ 灰色ACTUA狐狸頭LOGO休閒五分褲-XS，，MAISON KITSUNÉ\nMAISON KITSUNÉ 灰色ACTUA狐狸頭LOGO休閒五分褲-XL\nMAISON KITSUNÉ 灰色ACTUA狐狸頭LOGO休閒五分褲-XL，，MAISON KITSUNÉ\nMAISON KITSUNÉ 灰色ACTUA狐狸頭LOGO休閒五分褲--S\nMAISON KITSUNÉ 灰色ACTUA狐狸頭LOGO休閒五分褲--S，，MAISON KITSUNÉ\nMAISON KITSUNÉ 灰色ACTUA狐狸頭LOGO休閒五分褲--M\nMAISON KITSUNÉ 灰色ACTUA狐狸頭LOGO休閒五分褲--M，，MAISON KITSUNÉ\nMAISON KITSUNÉ 灰色ACTUA狐狸頭LOGO休閒五分褲--L\nMAISON KITSUNÉ 灰色ACTUA狐狸頭LOGO休閒五分褲--L，，MAISON KITSUNÉ\nMAISON KITSUNÉ 水藍ACTUA狐狸頭LOGO休閒短褲-XS\nMAISON KITSUNÉ 水藍ACTUA狐狸頭LOGO休閒短褲-XS，，MAISON KITSUNÉ\nMAISON KITSUNÉ 水藍ACTUA狐狸頭LOGO休閒短褲-XL\nMAISON KITSUNÉ 水藍ACTUA狐狸頭LOGO休閒短褲-XL，，MAISON KITSUNÉ", "language": null, "image": "https://www.eslite.com/eslite-og-logo.png", "pagetype": "Article", "source": "https://www.eslite.com/category/3/25598", "source-hostname": "短褲．長褲．牛仔褲｜法國小狐狸｜服飾鞋包｜誠品線上", "excerpt": "短褲．長褲．牛仔褲類-提供各種短褲．長褲．牛仔褲新品及優惠商品。誠品以「人文、藝術、創意、生活」為核心價值，由推廣閱讀出發，並透過線上網路，傳遞博雅的溫度，打造全新的文化場域。", "categories": "", "tags": ""}