{"title": "壓克力展示架 盒｜基礎辦公文具➤｜文具潮藝｜誠品線上", "author": null, "hostname": "eslite.com", "date": "2023-01-01", "fingerprint": "f4136427d51f6e21", "id": null, "license": null, "comments": "", "raw_text": "壓克力展示盒-長型  壓克力展示盒-長型，，育昌  新感覺拼圖式組合壓克力展示盒  新感覺拼圖式組合壓克力展示盒，，育昌  徠福 壓克力座席卡架20*7*6cm 20入  徠福 壓克力座席卡架20*7*6cm 20入，，徠福  徠福 壓克力座席卡架17.5*7*6cm 20入  徠福 壓克力座席卡架17.5*7*6cm 20入，，徠福  徠福 壓克力座席卡架15*7*6cm 20入  徠福 壓克力座席卡架15*7*6cm 20入，，徠福  徠福 壓克力座席卡架13*7*6cm 20入  徠福 壓克力座席卡架13*7*6cm 20入，，徠福  徠福 壓克力座席卡架11.5*6.5*6cm 20入  徠福 壓克力座席卡架11.5*6.5*6cm 20入，，徠福  徠福 L型壓克力商品標示架-直式A4 5入  徠福 L型壓克力商品標示架-直式A4 5入，，徠福  徠福 L型壓克力商品標示架-橫式A4 5入  徠福 L型壓克力商品標示架-橫式A4 5入，，徠福", "text": "壓克力展示盒-長型\n壓克力展示盒-長型，，育昌\n新感覺拼圖式組合壓克力展示盒\n新感覺拼圖式組合壓克力展示盒，，育昌\n徠福 壓克力座席卡架20*7*6cm 20入\n徠福 壓克力座席卡架20*7*6cm 20入，，徠福\n徠福 壓克力座席卡架17.5*7*6cm 20入\n徠福 壓克力座席卡架17.5*7*6cm 20入，，徠福\n徠福 壓克力座席卡架15*7*6cm 20入\n徠福 壓克力座席卡架15*7*6cm 20入，，徠福\n徠福 壓克力座席卡架13*7*6cm 20入\n徠福 壓克力座席卡架13*7*6cm 20入，，徠福\n徠福 壓克力座席卡架11.5*6.5*6cm 20入\n徠福 壓克力座席卡架11.5*6.5*6cm 20入，，徠福\n徠福 L型壓克力商品標示架-直式A4 5入\n徠福 L型壓克力商品標示架-直式A4 5入，，徠福\n徠福 L型壓克力商品標示架-橫式A4 5入\n徠福 L型壓克力商品標示架-橫式A4 5入，，徠福", "language": null, "image": "https://www.eslite.com/eslite-og-logo.png", "pagetype": "Article", "source": "https://www.eslite.com/category/3/14429", "source-hostname": "壓克力展示架 盒｜基礎辦公文具➤｜文具潮藝｜誠品線上", "excerpt": "壓克力展示架 盒類-提供各種壓克力展示架 盒新品及優惠商品。誠品以「人文、藝術、創意、生活」為核心價值，由推廣閱讀出發，並透過線上網路，傳遞博雅的溫度，打造全新的文化場域。", "categories": "", "tags": ""}