{"title": "前衛 重搖滾｜西洋CD｜影音｜誠品線上", "author": null, "hostname": "eslite.com", "date": "2023-09-19", "fingerprint": "c6891c12152b8d4d", "id": null, "license": null, "comments": "", "raw_text": "史密斯飛船: 成軍50週年傳奇精選 (3CD/豪華盤)  史密斯飛船: 成軍50週年傳奇精選 (3CD/豪華盤)，Aerosmith: Greatest Hits (3CD/Deluxe Edition)，  摘星者  摘星者，Starcatcher，Josh Kiszka/ Jake Kiszka/ Sam Kiszka/ Danny Wagner  71/17 Another Green Journey (2CD)  71/17 Another Green Journey (2CD)，，  Dante XXI (CD/Digipak)  Dante XXI (CD/Digipak)，，  A-Lex (CD/Digipak)  A-Lex (CD/Digipak)，，  Forgotten In Space (5CD+DVD/Deluxe Edition)  Forgotten In Space (5CD+DVD/Deluxe Edition)，，  The Amazing Kamikaze Syndrome (CD/Mediabook)  The Amazing Kamikaze Syndrome (CD/Mediabook)，，  Crackers: The Christmas Party Album (CD)  Crackers: The Christmas Party Album (CD)，，  Sladest (CD/Expanded Mediabook)  Sladest (CD/Expanded Mediabook)，，  Nobody's Fools (CD/Mediabook)  Nobody's Fools (CD/Mediabook)，，  In Nomine Satanas (6CD+DVD/Box Set)  In Nomine Satanas (6CD+DVD/Box Set)，，  Against (CD/Digipak)  Against (CD/Digipak)，，  Step Into The Light (CD)  Step Into The Light (CD)，，  Nation (CD/Digipak)  Nation (CD/Digipak)，，  Ratt: The Atlantic Years 1984-1990 (5CD)  Ratt: The Atlantic Years 1984-1990 (5CD)，，  Inferno (CD/Digipak)  Inferno (CD/Digipak)，，  Hammered (CD/Digipak)  Hammered (CD/Digipak)，，  We Are Motorhead (CD/Digipak)  We Are Motorhead (CD/Digipak)，，  Snake Bite Love (CD/Digipak)  Snake Bite Love (CD/Digipak)，，  Overnight Sensation (CD)  Overnight Sensation (CD)，，  Sacrifice (CD/Digipak)  Sacrifice (CD/Digipak)，，  Iron Fist (2CD/40th Anniversary Edition)  Iron Fist (2CD/40th Anniversary Edition)，，  Dio At Donington '87 (CD/Limited Edition Digipak With Lenticular Cover)  Dio At Donington '87 (CD/Limited Edition Digipak With Lenticular Cover)，，Ronnie James Dio (Ronald James Padavona)/ Black Sabbath, Rainbow  Live Evil (4CD/40th Anniversary Super Deluxe Edition)  Live Evil (4CD/40th Anniversary Super Deluxe Edition)，罪惡現場 (4CD/四十週年豪華限量版)，Vinny Appice, Geezer Butler, Ronnie James Dio, Tony Iommi, Geoff Nicholls  Dio At Donington '83 (CD)  Dio At Donington '83 (CD)，，Ronnie James Dio (Ronald James Padavona)/ Black Sabbath, Rainbow  Crucial Crue: The Studio Albums 1981-1989 (5CD/Limited Edition)  Crucial Crue: The Studio Albums 1981-1989 (5CD/Limited Edition)，，Nikki Sixx, Tommy Lee  Dr. Feelgood (CD/Digipak)  Dr. Feelgood (CD/Digipak)，，Nikki Sixx, Tommy Lee  Dio At Donington '87 (CD)  Dio At Donington '87 (CD)，，Ronnie James Dio (Ronald James Padavona)/ Black Sabbath, Rainbow  Parallel Minds (CD)  Parallel Minds (CD)，，  Mob Rules (2CD)  Mob Rules (2CD)，暴民統治 (2CD)，Vinny Appice, Geezer Butler, Ronnie James Dio, Tony Iommi, Geoff Nicholls  Two Dreams (CD)  Two Dreams (CD)，，  Shout At The Devil (CD/Digipak)  Shout At The Devil (CD/Digipak)，，Nikki Sixx, Tommy Lee  Dio At Donington '83 (CD/Limited Edition Digipak with Lenticular Cover)  Dio At Donington '83 (CD/Limited Edition Digipak with Lenticular Cover)，，Ronnie James Dio (Ronald James Padavona)/ Black Sabbath, Rainbow  Dokken: The Elektra Albums 1983-1987 (4CD)  Dokken: The Elektra Albums 1983-1987 (4CD)，，  Flow (CD)  Flow (CD)，，  In Your Multitude (CD)  In Your Multitude (CD)，，  The Last Sunset (CD)  The Last Sunset (CD)，，  Intergalactic Demon King (CD/Digipak)  Intergalactic Demon King (CD/Digipak)，，  Chaos & Colour (CD/Digipak)  Chaos & Colour (CD/Digipak)，，  Chaos & Colour (CD/+Patch/Deluxe Edition)  Chaos & Colour (CD/+Patch/Deluxe Edition)，，", "text": "史密斯飛船: 成軍50週年傳奇精選 (3CD/豪華盤)\n史密斯飛船: 成軍50週年傳奇精選 (3CD/豪華盤)，Aerosmith: Greatest Hits (3CD/Deluxe Edition)，\n摘星者\n摘星者，Starcatcher，Josh Kiszka/ Jake Kiszka/ Sam Kiszka/ Danny Wagner\n71/17 Another Green Journey (2CD)\n71/17 Another Green Journey (2CD)，，\nDante XXI (CD/Digipak)\nDante XXI (CD/Digipak)，，\nA-Lex (CD/Digipak)\nA-Lex (CD/Digipak)，，\nForgotten In Space (5CD+DVD/Deluxe Edition)\nForgotten In Space (5CD+DVD/Deluxe Edition)，，\nThe Amazing Kamikaze Syndrome (CD/Mediabook)\nThe Amazing Kamikaze Syndrome (CD/Mediabook)，，\nCrackers: The Christmas Party Album (CD)\nCrackers: The Christmas Party Album (CD)，，\nSladest (CD/Expanded Mediabook)\nSladest (CD/Expanded Mediabook)，，\nNobody's Fools (CD/Mediabook)\nNobody's Fools (CD/Mediabook)，，\nIn Nomine Satanas (6CD+DVD/Box Set)\nIn Nomine Satanas (6CD+DVD/Box Set)，，\nAgainst (CD/Digipak)\nAgainst (CD/Digipak)，，\nStep Into The Light (CD)\nStep Into The Light (CD)，，\nNation (CD/Digipak)\nNation (CD/Digipak)，，\nRatt: The Atlantic Years 1984-1990 (5CD)\nRatt: The Atlantic Years 1984-1990 (5CD)，，\nInferno (CD/Digipak)\nInferno (CD/Digipak)，，\nHammered (CD/Digipak)\nHammered (CD/Digipak)，，\nWe Are Motorhead (CD/Digipak)\nWe Are Motorhead (CD/Digipak)，，\nSnake Bite Love (CD/Digipak)\nSnake Bite Love (CD/Digipak)，，\nOvernight Sensation (CD)\nOvernight Sensation (CD)，，\nSacrifice (CD/Digipak)\nSacrifice (CD/Digipak)，，\nIron Fist (2CD/40th Anniversary Edition)\nIron Fist (2CD/40th Anniversary Edition)，，\nDio At Donington '87 (CD/Limited Edition Digipak With Lenticular Cover)\nDio At Donington '87 (CD/Limited Edition Digipak With Lenticular Cover)，，Ronnie James Dio (Ronald James Padavona)/ Black Sabbath, Rainbow\nLive Evil (4CD/40th Anniversary Super Deluxe Edition)\nLive Evil (4CD/40th Anniversary Super Deluxe Edition)，罪惡現場 (4CD/四十週年豪華限量版)，Vinny Appice, Geezer Butler, Ronnie James Dio, Tony Iommi, Geoff Nicholls\nDio At Donington '83 (CD)\nDio At Donington '83 (CD)，，Ronnie James Dio (Ronald James Padavona)/ Black Sabbath, Rainbow\nCrucial Crue: The Studio Albums 1981-1989 (5CD/Limited Edition)\nCrucial Crue: The Studio Albums 1981-1989 (5CD/Limited Edition)，，Nikki Sixx, Tommy Lee\nDr. Feelgood (CD/Digipak)\nDr. Feelgood (CD/Digipak)，，Nikki Sixx, Tommy Lee\nDio At Donington '87 (CD)\nDio At Donington '87 (CD)，，Ronnie James Dio (Ronald James Padavona)/ Black Sabbath, Rainbow\nParallel Minds (CD)\nParallel Minds (CD)，，\nMob Rules (2CD)\nMob Rules (2CD)，暴民統治 (2CD)，Vinny Appice, Geezer Butler, Ronnie James Dio, Tony Iommi, Geoff Nicholls\nTwo Dreams (CD)\nTwo Dreams (CD)，，\nShout At The Devil (CD/Digipak)\nShout At The Devil (CD/Digipak)，，Nikki Sixx, Tommy Lee\nDio At Donington '83 (CD/Limited Edition Digipak with Lenticular Cover)\nDio At Donington '83 (CD/Limited Edition Digipak with Lenticular Cover)，，Ronnie James Dio (Ronald James Padavona)/ Black Sabbath, Rainbow\nDokken: The Elektra Albums 1983-1987 (4CD)\nDokken: The Elektra Albums 1983-1987 (4CD)，，\nFlow (CD)\nFlow (CD)，，\nIn Your Multitude (CD)\nIn Your Multitude (CD)，，\nThe Last Sunset (CD)\nThe Last Sunset (CD)，，\nIntergalactic Demon King (CD/Digipak)\nIntergalactic Demon King (CD/Digipak)，，\nChaos & Colour (CD/Digipak)\nChaos & Colour (CD/Digipak)，，\nChaos & Colour (CD/+Patch/Deluxe Edition)\nChaos & Colour (CD/+Patch/Deluxe Edition)，，", "language": null, "image": "https://www.eslite.com/eslite-og-logo.png", "pagetype": "Article", "source": "https://www.eslite.com/category/3/15506", "source-hostname": "前衛 重搖滾｜西洋Cd｜影音｜誠品線上", "excerpt": "前衛 重搖滾類-提供各種前衛 重搖滾新品及優惠商品。誠品以「人文、藝術、創意、生活」為核心價值，由推廣閱讀出發，並透過線上網路，傳遞博雅的溫度，打造全新的文化場域。", "categories": "", "tags": ""}