{"title": "日本 FELISSIMO｜療癒配件小物｜服飾鞋包｜誠品線上", "author": null, "hostname": "eslite.com", "date": null, "fingerprint": "93629ec2430c71f7", "id": null, "license": null, "comments": "", "raw_text": "FELISSIMO貓部貓咪肉球抽繩袋/ 黑  FELISSIMO貓部貓咪肉球抽繩袋/ 黑，，FELISSIMO/ Felissimo/ 日本  FELISSIMO貓部貓咪肉球抽繩袋/ 混和  FELISSIMO貓部貓咪肉球抽繩袋/ 混和，，FELISSIMO/ Felissimo/ 日本  FELISSIMO貓部貓咪肉球抽繩袋/ 深棕  FELISSIMO貓部貓咪肉球抽繩袋/ 深棕，，FELISSIMO/ Felissimo/ 日本  FELISSIMO貓部貓咪環保袋/ 黑色  FELISSIMO貓部貓咪環保袋/ 黑色，，FELISSIMO/ Felissimo/ 日本  FELISSIMO貓部貓咪環保袋/ 藍色  FELISSIMO貓部貓咪環保袋/ 藍色，，FELISSIMO/ Felissimo/ 日本  FELISSIMO貓部貓咪環保袋/ 米色  FELISSIMO貓部貓咪環保袋/ 米色，，FELISSIMO/ Felissimo/ 日本  FELISSIMO貓部貓咪收納包/ 黑白貓  FELISSIMO貓部貓咪收納包/ 黑白貓，，FELISSIMO/ Felissimo/ 日本  FELISSIMO貓部貓咪收納包/ 虎斑  FELISSIMO貓部貓咪收納包/ 虎斑，，FELISSIMO/ Felissimo/ 日本  FELISSIMO貓部貓咪收納包/ 三毛貓  FELISSIMO貓部貓咪收納包/ 三毛貓，，FELISSIMO/ Felissimo/ 日本  FELISSIMO貓部脹鼓鼓口金包/ 黑白貓  FELISSIMO貓部脹鼓鼓口金包/ 黑白貓，，FELISSIMO/ Felissimo/ 日本  FELISSIMO貓部與貓咪玩耍工作圍裙  FELISSIMO貓部與貓咪玩耍工作圍裙，，FELISSIMO/ 貓/ Felissimo/ 寵物/ 日本  FELISSIMO貓部脹鼓鼓口金包/ 黑白虎紋貓  FELISSIMO貓部脹鼓鼓口金包/ 黑白虎紋貓，，FELISSIMO/ Felissimo/ 日本  FELISSIMO貓部脹鼓鼓口金包/ 灰白貓  FELISSIMO貓部脹鼓鼓口金包/ 灰白貓，，FELISSIMO/ Felissimo/ 日本  FELISSIMO貓部脹鼓鼓口金包/ 灰黃虎斑貓  FELISSIMO貓部脹鼓鼓口金包/ 灰黃虎斑貓，，FELISSIMO/ Felissimo/ 日本  FELISSIMO貓部脹鼓鼓口金包/ 三毛貓  FELISSIMO貓部脹鼓鼓口金包/ 三毛貓，，FELISSIMO/ Felissimo/ 日本  FELISSIMO貓部小貓牛奶化妝包/ 黑白貓  FELISSIMO貓部小貓牛奶化妝包/ 黑白貓，，FELISSIMO/ Felissimo/ 日本  FELISSIMO貓部小貓牛奶化妝包/ 紅虎斑雙色  FELISSIMO貓部小貓牛奶化妝包/ 紅虎斑雙色，，FELISSIMO/ Felissimo/ 日本  FELISSIMO貓部小貓牛奶化妝包/ 白貓  FELISSIMO貓部小貓牛奶化妝包/ 白貓，，FELISSIMO/ Felissimo/ 日本  FELISSIMO貓部小貓牛奶化妝包/ 灰黃虎斑  FELISSIMO貓部小貓牛奶化妝包/ 灰黃虎斑，，FELISSIMO/ Felissimo/ 日本  FELISSIMO貓部購物袋風手提包  FELISSIMO貓部購物袋風手提包，，FELISSIMO/ Felissimo/ 日本  FELISSIMO豚鼠收納包/ 紅虎斑雙色  FELISSIMO豚鼠收納包/ 紅虎斑雙色，，FELISSIMO/ Felissimo/ 日本  FELISSIMO豚鼠收納包/ 奶油  FELISSIMO豚鼠收納包/ 奶油，，FELISSIMO/ Felissimo/ 日本  FELISSIMO豚鼠收納包/ 三毛  FELISSIMO豚鼠收納包/ 三毛，，FELISSIMO/ Felissimo/ 日本  FELISSIMO海獺收納包/ 驚嚇臉  FELISSIMO海獺收納包/ 驚嚇臉，，FELISSIMO/ Felissimo/ 日本  FELISSIMO海獺收納包/ 正常臉  FELISSIMO海獺收納包/ 正常臉，，FELISSIMO/ Felissimo/ 日本  FELISSIMO海獺收納包/ 休息臉  FELISSIMO海獺收納包/ 休息臉，，FELISSIMO/ Felissimo/ 日本  FELISSIMO挪亞方舟化妝包  FELISSIMO挪亞方舟化妝包，，FELISSIMO/ Felissimo/ 日本  FELISSIMO拉絲納豆卡套  FELISSIMO拉絲納豆卡套，，FELISSIMO/ Felissimo/ 日本  FELISSIMO冰淇淋收納包/ 雙球甜筒  FELISSIMO冰淇淋收納包/ 雙球甜筒，，FELISSIMO/ Felissimo/ 日本  FELISSIMO冰淇淋收納包/ 綜合杯裝  FELISSIMO冰淇淋收納包/ 綜合杯裝，，FELISSIMO/ Felissimo/ 日本  FELISSIMO冰淇淋收納包/ 單球甜筒  FELISSIMO冰淇淋收納包/ 單球甜筒，，FELISSIMO/ Felissimo/ 日本  FELISSIMO倉鼠束口袋/ 粉紅  FELISSIMO倉鼠束口袋/ 粉紅，，FELISSIMO/ Felissimo/ 日本  FELISSIMO倉鼠束口袋/ 黃  FELISSIMO倉鼠束口袋/ 黃，，FELISSIMO/ Felissimo/ 日本  FELISSIMO倉鼠束口袋/ 卡其  FELISSIMO倉鼠束口袋/ 卡其，，FELISSIMO/ Felissimo/ 日本  FELISSIMO倉鼠手帕/ 加卡利亞倉鼠  FELISSIMO倉鼠手帕/ 加卡利亞倉鼠，，FELISSIMO/ Felissimo/ 日本  日本 FELISSIMO 花繪圖騰裝飾環保袋/ 橘色  日本 FELISSIMO 花繪圖騰裝飾環保袋/ 橘色，，FELISSIMO  日本 FELISSIMO 花繪圖騰裝飾環保袋/ 柳綠色  日本 FELISSIMO 花繪圖騰裝飾環保袋/ 柳綠色，，FELISSIMO  日本 FELISSIMO 花繪圖騰裝飾環保袋/ 藍灰色  日本 FELISSIMO 花繪圖騰裝飾環保袋/ 藍灰色，，FELISSIMO  日本 FELISSIMO YOU+MORE! 軟Q倉鼠收納包/ 楓葉鼠  日本 FELISSIMO YOU+MORE! 軟Q倉鼠收納包/ 楓葉鼠，，FELISSIMO  日本 FELISSIMO YOU+MORE! 軟Q倉鼠收納包/ 杏色倉鼠  日本 FELISSIMO YOU+MORE! 軟Q倉鼠收納包/ 杏色倉鼠，，FELISSIMO", "text": "FELISSIMO貓部貓咪肉球抽繩袋/ 黑\nFELISSIMO貓部貓咪肉球抽繩袋/ 黑，，FELISSIMO/ Felissimo/ 日本\nFELISSIMO貓部貓咪肉球抽繩袋/ 混和\nFELISSIMO貓部貓咪肉球抽繩袋/ 混和，，FELISSIMO/ Felissimo/ 日本\nFELISSIMO貓部貓咪肉球抽繩袋/ 深棕\nFELISSIMO貓部貓咪肉球抽繩袋/ 深棕，，FELISSIMO/ Felissimo/ 日本\nFELISSIMO貓部貓咪環保袋/ 黑色\nFELISSIMO貓部貓咪環保袋/ 黑色，，FELISSIMO/ Felissimo/ 日本\nFELISSIMO貓部貓咪環保袋/ 藍色\nFELISSIMO貓部貓咪環保袋/ 藍色，，FELISSIMO/ Felissimo/ 日本\nFELISSIMO貓部貓咪環保袋/ 米色\nFELISSIMO貓部貓咪環保袋/ 米色，，FELISSIMO/ Felissimo/ 日本\nFELISSIMO貓部貓咪收納包/ 黑白貓\nFELISSIMO貓部貓咪收納包/ 黑白貓，，FELISSIMO/ Felissimo/ 日本\nFELISSIMO貓部貓咪收納包/ 虎斑\nFELISSIMO貓部貓咪收納包/ 虎斑，，FELISSIMO/ Felissimo/ 日本\nFELISSIMO貓部貓咪收納包/ 三毛貓\nFELISSIMO貓部貓咪收納包/ 三毛貓，，FELISSIMO/ Felissimo/ 日本\nFELISSIMO貓部脹鼓鼓口金包/ 黑白貓\nFELISSIMO貓部脹鼓鼓口金包/ 黑白貓，，FELISSIMO/ Felissimo/ 日本\nFELISSIMO貓部與貓咪玩耍工作圍裙\nFELISSIMO貓部與貓咪玩耍工作圍裙，，FELISSIMO/ 貓/ Felissimo/ 寵物/ 日本\nFELISSIMO貓部脹鼓鼓口金包/ 黑白虎紋貓\nFELISSIMO貓部脹鼓鼓口金包/ 黑白虎紋貓，，FELISSIMO/ Felissimo/ 日本\nFELISSIMO貓部脹鼓鼓口金包/ 灰白貓\nFELISSIMO貓部脹鼓鼓口金包/ 灰白貓，，FELISSIMO/ Felissimo/ 日本\nFELISSIMO貓部脹鼓鼓口金包/ 灰黃虎斑貓\nFELISSIMO貓部脹鼓鼓口金包/ 灰黃虎斑貓，，FELISSIMO/ Felissimo/ 日本\nFELISSIMO貓部脹鼓鼓口金包/ 三毛貓\nFELISSIMO貓部脹鼓鼓口金包/ 三毛貓，，FELISSIMO/ Felissimo/ 日本\nFELISSIMO貓部小貓牛奶化妝包/ 黑白貓\nFELISSIMO貓部小貓牛奶化妝包/ 黑白貓，，FELISSIMO/ Felissimo/ 日本\nFELISSIMO貓部小貓牛奶化妝包/ 紅虎斑雙色\nFELISSIMO貓部小貓牛奶化妝包/ 紅虎斑雙色，，FELISSIMO/ Felissimo/ 日本\nFELISSIMO貓部小貓牛奶化妝包/ 白貓\nFELISSIMO貓部小貓牛奶化妝包/ 白貓，，FELISSIMO/ Felissimo/ 日本\nFELISSIMO貓部小貓牛奶化妝包/ 灰黃虎斑\nFELISSIMO貓部小貓牛奶化妝包/ 灰黃虎斑，，FELISSIMO/ Felissimo/ 日本\nFELISSIMO貓部購物袋風手提包\nFELISSIMO貓部購物袋風手提包，，FELISSIMO/ Felissimo/ 日本\nFELISSIMO豚鼠收納包/ 紅虎斑雙色\nFELISSIMO豚鼠收納包/ 紅虎斑雙色，，FELISSIMO/ Felissimo/ 日本\nFELISSIMO豚鼠收納包/ 奶油\nFELISSIMO豚鼠收納包/ 奶油，，FELISSIMO/ Felissimo/ 日本\nFELISSIMO豚鼠收納包/ 三毛\nFELISSIMO豚鼠收納包/ 三毛，，FELISSIMO/ Felissimo/ 日本\nFELISSIMO海獺收納包/ 驚嚇臉\nFELISSIMO海獺收納包/ 驚嚇臉，，FELISSIMO/ Felissimo/ 日本\nFELISSIMO海獺收納包/ 正常臉\nFELISSIMO海獺收納包/ 正常臉，，FELISSIMO/ Felissimo/ 日本\nFELISSIMO海獺收納包/ 休息臉\nFELISSIMO海獺收納包/ 休息臉，，FELISSIMO/ Felissimo/ 日本\nFELISSIMO挪亞方舟化妝包\nFELISSIMO挪亞方舟化妝包，，FELISSIMO/ Felissimo/ 日本\nFELISSIMO拉絲納豆卡套\nFELISSIMO拉絲納豆卡套，，FELISSIMO/ Felissimo/ 日本\nFELISSIMO冰淇淋收納包/ 雙球甜筒\nFELISSIMO冰淇淋收納包/ 雙球甜筒，，FELISSIMO/ Felissimo/ 日本\nFELISSIMO冰淇淋收納包/ 綜合杯裝\nFELISSIMO冰淇淋收納包/ 綜合杯裝，，FELISSIMO/ Felissimo/ 日本\nFELISSIMO冰淇淋收納包/ 單球甜筒\nFELISSIMO冰淇淋收納包/ 單球甜筒，，FELISSIMO/ Felissimo/ 日本\nFELISSIMO倉鼠束口袋/ 粉紅\nFELISSIMO倉鼠束口袋/ 粉紅，，FELISSIMO/ Felissimo/ 日本\nFELISSIMO倉鼠束口袋/ 黃\nFELISSIMO倉鼠束口袋/ 黃，，FELISSIMO/ Felissimo/ 日本\nFELISSIMO倉鼠束口袋/ 卡其\nFELISSIMO倉鼠束口袋/ 卡其，，FELISSIMO/ Felissimo/ 日本\nFELISSIMO倉鼠手帕/ 加卡利亞倉鼠\nFELISSIMO倉鼠手帕/ 加卡利亞倉鼠，，FELISSIMO/ Felissimo/ 日本\n日本 FELISSIMO 花繪圖騰裝飾環保袋/ 橘色\n日本 FELISSIMO 花繪圖騰裝飾環保袋/ 橘色，，FELISSIMO\n日本 FELISSIMO 花繪圖騰裝飾環保袋/ 柳綠色\n日本 FELISSIMO 花繪圖騰裝飾環保袋/ 柳綠色，，FELISSIMO\n日本 FELISSIMO 花繪圖騰裝飾環保袋/ 藍灰色\n日本 FELISSIMO 花繪圖騰裝飾環保袋/ 藍灰色，，FELISSIMO\n日本 FELISSIMO YOU+MORE! 軟Q倉鼠收納包/ 楓葉鼠\n日本 FELISSIMO YOU+MORE! 軟Q倉鼠收納包/ 楓葉鼠，，FELISSIMO\n日本 FELISSIMO YOU+MORE! 軟Q倉鼠收納包/ 杏色倉鼠\n日本 FELISSIMO YOU+MORE! 軟Q倉鼠收納包/ 杏色倉鼠，，FELISSIMO", "language": null, "image": "https://www.eslite.com/eslite-og-logo.png", "pagetype": "Article", "source": "https://www.eslite.com/category/3/11523", "source-hostname": "日本 Felissimo｜療癒配件小物｜服飾鞋包｜誠品線上", "excerpt": "日本 FELISSIMO類-提供各種日本 FELISSIMO新品及優惠商品。誠品以「人文、藝術、創意、生活」為核心價值，由推廣閱讀出發，並透過線上網路，傳遞博雅的溫度，打造全新的文化場域。", "categories": "", "tags": ""}